README.rst
setup.py
m2wsgid.egg-info/PKG-INFO
m2wsgid.egg-info/SOURCES.txt
m2wsgid.egg-info/dependency_links.txt
m2wsgid.egg-info/requires.txt
m2wsgid.egg-info/top_level.txt
scripts/wsgid
wsgid/__init__.py
wsgid/conf.py
wsgid/test.py
wsgid/commands/__init__.py
wsgid/commands/config.py
wsgid/commands/init.py
wsgid/commands/manage.py
wsgid/commands/status.py
wsgid/core/__init__.py
wsgid/core/cli.py
wsgid/core/command.py
wsgid/core/message.py
wsgid/core/parser.py
wsgid/interfaces/__init__.py
wsgid/interfaces/filters.py
wsgid/loaders/__init__.py
wsgid/loaders/djangoloader.py