Metadata-Version: 1.1
Name: m2wsgid
Version: 0.7.1
Summary: A complete WSGI environment for mongrel2 handlers
Home-page: https://github.com/daltonmatos/wsgid
Author: Dalton Barreto
Author-email: daltonmatos@gmail.com
License: 3-BSD
Platform: UNKNOWN
Classifier: License :: OSI Approved :: BSD License
Classifier: Operating System :: OS Independent
Classifier: Programming Language :: Python
Classifier: Topic :: Software Development :: Libraries :: Application Frameworks
